web_extractor/__init__.py
web_extractor/server.py
mcp_web_extractor_sadasiba-0.1.3.dist-info/METADATA
mcp_web_extractor_sadasiba-0.1.3.dist-info/WHEEL
mcp_web_extractor_sadasiba-0.1.3.dist-info/entry_points.txt
mcp_web_extractor_sadasiba-0.1.3.dist-info/top_level.txt
mcp_web_extractor_sadasiba-0.1.3.dist-info/RECORD
